yv/__init__.py
yv-0.0.6.dist-info/licenses/LICENSE
yv-0.0.6.dist-info/METADATA
yv-0.0.6.dist-info/WHEEL
yv-0.0.6.dist-info/top_level.txt
yv-0.0.6.dist-info/RECORD
