Metadata-Version: 2.4
Name: yv
Version: 0.0.6
Summary: Simple utils to get stuff out of Mappings (dict-like objects).
Home-page: https://github.com/t-c-w/yv
Author: Thor Whalen
License: apache-2.0
Platform: any
License-File: LICENSE
Dynamic: license-file
